pytest_flake8.py
pytest_flake8-1.3.0.dist-info/LICENSE
pytest_flake8-1.3.0.dist-info/METADATA
pytest_flake8-1.3.0.dist-info/WHEEL
pytest_flake8-1.3.0.dist-info/entry_points.txt
pytest_flake8-1.3.0.dist-info/top_level.txt
pytest_flake8-1.3.0.dist-info/RECORD
